{
  "one": {
    "title": "One",
    "content": "这是一级目录 One",
    "list": {
      "one-one": {
        "title": "这是二级目录",
        "content": "这是二级目录 One-One",
        "list": {
          "one-one-one": {
            "title": "这是三级目录",
            "content": "这是三级目录 One-One-One",
            "list": {
              "one-one-one-one.md": {
                "title": "这是四级文件",
                "content": "这是四级文件 One"
              },
              "one-one-one-two.md": {
                "title": "这是四级文件",
                "content": "这是四级文件 Two"
              }
            }
          },
          "one-one-two.md": {
            "title": "这是三级文件",
            "content": "这是三级文件 One-One-Two"
          },
          "one-one-three.md": {
            "title": "这是三级文件",
            "content": "这是三级文件 One-One-Three"
          }
        }
      }
    }
  },
  "two": {
    "title": "Two",
    "content": "这是一级目录 Two",
    "list": {
      "two-one.md": {
        "title": "这是二级目录",
        "content": "这是二级目录 Two-One"
      }
    }
  },
  "three": {
    "title": "Three",
    "content": "这是一级目录 Three",
    "list": {
      "three-one.md": {
        "title": "这是二级目录",
        "content": "这是二级目录 Three-One"
      }
    }
  }
}
